collective.linkconsentinfo-1.4-py3.11-nspkg.pth
collective/linkconsentinfo/__init__.py
collective/linkconsentinfo/configure.zcml
collective/linkconsentinfo/interfaces.py
collective/linkconsentinfo/overrides.zcml
collective/linkconsentinfo/permissions.zcml
collective/linkconsentinfo/setuphandlers.py
collective/linkconsentinfo/testing.py
collective/linkconsentinfo/behaviors/__init__.py
collective/linkconsentinfo/behaviors/configure.zcml
collective/linkconsentinfo/behaviors/link_consent_info_behavior.py
collective/linkconsentinfo/browser/__init__.py
collective/linkconsentinfo/browser/configure.zcml
collective/linkconsentinfo/browser/overrides/.gitkeep
collective/linkconsentinfo/browser/static/.gitkeep
collective/linkconsentinfo/controlpanels/__init__.py
collective/linkconsentinfo/controlpanels/configure.zcml
collective/linkconsentinfo/controlpanels/link_consent_info.py
collective/linkconsentinfo/indexers/__init__.py
collective/linkconsentinfo/indexers/configure.zcml
collective/linkconsentinfo/indexers/get_remote_url.py
collective/linkconsentinfo/locales/README.rst
collective/linkconsentinfo/locales/__init__.py
collective/linkconsentinfo/locales/collective.linkconsentinfo.pot
collective/linkconsentinfo/locales/update.py
collective/linkconsentinfo/locales/update.sh
collective/linkconsentinfo/locales/__pycache__/LC_MESSAGES/collective.linkconsentinfo.po
collective/linkconsentinfo/locales/de/LC_MESSAGES/collective.linkconsentinfo.po
collective/linkconsentinfo/locales/en/LC_MESSAGES/collective.linkconsentinfo.po
collective/linkconsentinfo/profiles/default/browserlayer.xml
collective/linkconsentinfo/profiles/default/catalog.xml
collective/linkconsentinfo/profiles/default/controlpanel.xml
collective/linkconsentinfo/profiles/default/metadata.xml
collective/linkconsentinfo/profiles/default/rolemap.xml
collective/linkconsentinfo/profiles/default/registry/link_consent_info_control_panel.xml
collective/linkconsentinfo/profiles/default/registry/main.xml
collective.linkconsentinfo-1.4.dist-info/LICENSE.GPL
collective.linkconsentinfo-1.4.dist-info/LICENSE.rst
collective.linkconsentinfo-1.4.dist-info/METADATA
collective.linkconsentinfo-1.4.dist-info/WHEEL
collective.linkconsentinfo-1.4.dist-info/entry_points.txt
collective.linkconsentinfo-1.4.dist-info/namespace_packages.txt
collective.linkconsentinfo-1.4.dist-info/top_level.txt
collective.linkconsentinfo-1.4.dist-info/RECORD
